setup.py
txmandrill.py
txmandrill.egg-info/PKG-INFO
txmandrill.egg-info/SOURCES.txt
txmandrill.egg-info/dependency_links.txt
txmandrill.egg-info/requires.txt
txmandrill.egg-info/top_level.txt