Metadata-Version: 1.1
Name: txmandrill
Version: 1.0.0
Summary: The Mandrill Python client but for Twisted..
Home-page: https://github.com/lextoumbourou/txmandrill-api
Author: Lex Toumbourou
Author-email: lextoumbourou@gmail.com
License: Apache
Platform: UNKNOWN
Classifier: Programming Language :: Python
Classifier: Programming Language :: Python :: 2
Classifier: Programming Language :: Python :: 2.6
Classifier: Programming Language :: Python :: 2.7
